image_processing_toolkit_wwy/__init__.py
image_processing_toolkit_wwy/analyze.py
image_processing_toolkit_wwy/convert.py
image_processing_toolkit_wwy/filters.py
image_processing_toolkit_wwy-1.0.0.dist-info/LICENSE
image_processing_toolkit_wwy-1.0.0.dist-info/METADATA
image_processing_toolkit_wwy-1.0.0.dist-info/WHEEL
image_processing_toolkit_wwy-1.0.0.dist-info/entry_points.txt
image_processing_toolkit_wwy-1.0.0.dist-info/top_level.txt
image_processing_toolkit_wwy-1.0.0.dist-info/RECORD
