Metadata-Version: 2.1
Name: image_processing_toolkit_wwy
Version: 1.0.0
Summary: A simple toolkit for image processing
Home-page: http://www.example.com
Author: 202313093029_.wwy
Author-email: 202313093029@cuc.edu.cn
Classifier: Programming Language :: Python :: 3
Classifier: License :: OSI Approved :: MIT License
Classifier: Operating System :: OS Independent
Requires-Python: >=3.6
License-File: LICENSE
Requires-Dist: Pillow
Provides-Extra: dev
Requires-Dist: check-manifest; extra == "dev"
Provides-Extra: test
Requires-Dist: coverage; extra == "test"
